{
  "hello": {
    "calls": [
      {
        "keywords": [
          "hello"
        ]
      },
      {
        "keywords": [
          "hi"
        ]
      },
      {
        "keywords": [
          "good",
          "morning"
        ]
      },
      {
        "keywords": [
          "hey"
        ]
      }
    ]
  },
  "how_are_you": {
    "calls": [
      {
        "keywords": [
          "how",
          "are",
          "you"
        ]
      }
    ]
  },
  "who_are_you": {
    "calls": [
      {
        "keywords": [
          "who",
          "are",
          "you"
        ]
      },
      {
        "keywords": [
          "introduce",
          "yourself"
        ]
      }
    ]
  },
  "mona": {
    "calls": [
      {
        "keywords": [
          "mona"
        ]
      }
    ]
  }
}